narrative2vec/__init__.py
narrative2vec/narrative.py
narrative2vec/narrative_csv.py
narrative2vec/constants/__init__.py
narrative2vec/constants/action_table_header.py
narrative2vec/constants/poses.py
narrative2vec/constants/reasoning_task_table_header.py
narrative2vec/logging_instance/__init__.py
narrative2vec/logging_instance/action.py
narrative2vec/logging_instance/logging_instance.py
narrative2vec/logging_instance/pose.py
narrative2vec/logging_instance/reasoning_task.py
narrative2vec/ontology/__init__.py
narrative2vec/ontology/neemNarrativeDefinitions.py
narrative2vec/ontology/ontologyHandler.py
narrative2vec/ontology/uriDefinitions.py
narrative2vec/reasoning_task/__init__.py
narrative2vec/test/__init__.py
narrative2vec/test/narrative_test.py
neem/__init__.py
neem/narrative.py
neem/narrative_csv.py
neem/constants/__init__.py
neem/constants/action_table_header.py
neem/constants/poses.py
neem/constants/reasoning_task_table_header.py
neem/logging_instance/__init__.py
neem/logging_instance/action.py
neem/logging_instance/logging_instance.py
neem/logging_instance/pose.py
neem/logging_instance/reasoning_task.py
neem/ontology/__init__.py
neem/ontology/neemNarrativeDefinitions.py
neem/ontology/ontologyHandler.py
neem/ontology/uriDefinitions.py
neem/reasoning_task/__init__.py
neem/test/__init__.py
neem/test/narrative_test.py
narrative2vec-4.0.1.dist-info/LICENSE
narrative2vec-4.0.1.dist-info/METADATA
narrative2vec-4.0.1.dist-info/WHEEL
narrative2vec-4.0.1.dist-info/top_level.txt
narrative2vec-4.0.1.dist-info/RECORD
