Metadata-Version: 2.1
Name: narrative2vec
Version: 4.0.1
Summary: Transforms NEEM narrative data into CSV files
Home-page: https://github.com/code-iai/narrative2vec
Author: Sebastian Koralewski
Author-email: seba@cs.uni-bremen.de
License: UNKNOWN
Platform: UNKNOWN
Classifier: Programming Language :: Python :: 2
Classifier: License :: OSI Approved :: MIT License
Classifier: Operating System :: OS Independent
Requires-Dist: rdflib (==4.2.2)
